usualsuspects/__init__.py
usualsuspects/pca.py
usualsuspects/tsne.py
usualsuspects/utils.py
usualsuspects-0.2.1.dist-info/LICENSE
usualsuspects-0.2.1.dist-info/METADATA
usualsuspects-0.2.1.dist-info/WHEEL
usualsuspects-0.2.1.dist-info/top_level.txt
usualsuspects-0.2.1.dist-info/RECORD
