Metadata-Version: 2.1
Name: usualsuspects
Version: 0.2.1
Summary: Some quick tools for generating visualisations that pop up in ML papers all the time
Home-page: https://github.com/paulmorio/usualsuspects
Author: Paul Scherer
Author-email: paul.geo2dr@gmail.com
License: MIT
Platform: UNKNOWN
Classifier: Topic :: Scientific/Engineering :: Artificial Intelligence
Classifier: License :: OSI Approved :: MIT License
Classifier: Natural Language :: English
Classifier: Programming Language :: Python :: 3.6
Classifier: Operating System :: OS Independent
Requires-Dist: numpy
Requires-Dist: scikit-learn
Requires-Dist: tqdm
Requires-Dist: matplotlib
